panda_color/__init__.py
panda_color/color.py
panda_color/color.pyi
panda_color/util.py
panda_color/util.pyi
panda_color-0.1.4.4.dist-info/licenses/LICENSE
panda_color-0.1.4.4.dist-info/METADATA
panda_color-0.1.4.4.dist-info/WHEEL
panda_color-0.1.4.4.dist-info/top_level.txt
panda_color-0.1.4.4.dist-info/RECORD
