Metadata-Version: 2.4
Name: panda-color
Version: 0.1.4.4
Summary: A color library that supports RGB with swizzling and will support hex and hsv in the future
Author-email: Colin Politi <urboycolinthepanda@gmail.com>
License-Expression: MIT
Project-URL: Homepage, https://github.com/ColinThePanda/PandaColor
Project-URL: Bug Tracker, https://github.com/ColinThePanda/PandaColor/issues
Classifier: Programming Language :: Python :: 3
Classifier: Operating System :: OS Independent
Requires-Python: >=3.9
License-File: LICENSE
Dynamic: license-file
